{
  "cycloneMessage": {
    "advisoryNumber": "4",
    "atcfID": "EP062017",
    "centerLocLatitude": "11.8",
    "centerLocLatitudeExpanded": "11.8N",
    "centerLocLongitude": "-112.2",
    "centerLocLongitudeExpanded": "112.2W",
    "formationChancePct48h": "N/A",
    "formationChancePct5d": "N/A",
    "issuingUnit": "NWS NATIONAL HURRICANE CENTER MIAMI FL",
    "message": "ZCZC MIATCPEP1 ALL\nTTAA00 KNHC DDHHMM\n\nBULLETIN\nTropical Storm Fernanda Advisory Number   4\nNWS National Hurricane Center Miami FL       EP062017\n300 PM MDT Wed Jul 12 2017\n\n...FERNANDA EXPECTED TO STRENGTHEN AS IT MOVES WESTWARD...\n\n\nSUMMARY OF 300 PM MDT...2100 UTC...INFORMATION\n----------------------------------------------\nLOCATION...11.8N 112.2W\nABOUT 780 MI...1255 KM SSW OF THE SOUTHERN TIP OF BAJA CALIFORNIA\nMAXIMUM SUSTAINED WINDS...40 MPH...65 KM/H\nPRESENT MOVEMENT...W OR 265 DEGREES AT 9 MPH...15 KM/H\nMINIMUM CENTRAL PRESSURE...1005 MB...29.68 INCHES\n\n\nWATCHES AND WARNINGS\n--------------------\nThere are no coastal watches or warnings in effect.\n\n\nDISCUSSION AND 48-HOUR OUTLOOK\n------------------------------\nAt 300 PM MDT (2100 UTC), the center of Tropical Storm Fernanda was\nlocated near latitude 11.8 North, longitude 112.2 West. Fernanda is\nmoving toward the west near 9 mph (15 km/h) and this general motion\nis expected to continue for the next couple of days.\n\nMaximum sustained winds are near 40 mph (65 km/h) with higher gusts.\nStrengthening is forecast during the next 48 hours, and Fernanda\ncould become a hurricane on Friday.\n\nRecent satellite wind data indicate that Fernanda is a small\ntropical storm, and tropical-storm-force winds extend outward up to\n25 miles (35 km) from the center.\n\nThe estimated minimum central pressure is 1005 mb (29.68 inches).\n\n\nHAZARDS AFFECTING LAND\n----------------------\nNone\n\n\nNEXT ADVISORY\n-------------\nNext complete advisory at 900 PM MDT.\n\n$$\nForecaster Beven\n\nNNNN",
    "messageBinNumber": "1",
    "messageDateTimeLocal": "20170712 03:00:00 PM MDT",
    "messageDateTimeLocalStr": "0300 PM MDT Wed Jul 12",
    "messageDateTimeUTC": "20170712 09:00:00 PM UTC",
    "messageDateTimeUTC24": "201707122100",
    "messageType": "ROUTINE ADVISORY",
    "systemDirectionOfMotion": "W OR 265 DEGREES",
    "systemGeoRefPt1": "ABOUT 780 MI...1255 KM SSW OF THE SOUTHERN TIP OF BAJA CALIFORNIA",
    "systemIntensityKph": "65",
    "systemIntensityKts": "35",
    "systemIntensityMph": "40",
    "systemMslpInHg": "29.68",
    "systemMslpMb": "1005",
    "systemName": "FERNANDA",
    "systemSaffirSimpsonCategory": "N/A",
    "systemSpeedKph": "15",
    "systemSpeedKts": "8",
    "systemSpeedMph": "9",
    "systemType": "TROPICAL STORM",
    "timeEpochSeconds": "1499893200"
  }
}
